odoo/addons/delivery_package_type_number_parcels/README.rst
odoo/addons/delivery_package_type_number_parcels/__init__.py
odoo/addons/delivery_package_type_number_parcels/__manifest__.py
odoo/addons/delivery_package_type_number_parcels/i18n/delivery_package_type_number_parcels.pot
odoo/addons/delivery_package_type_number_parcels/i18n/es.po
odoo/addons/delivery_package_type_number_parcels/i18n/it.po
odoo/addons/delivery_package_type_number_parcels/models/__init__.py
odoo/addons/delivery_package_type_number_parcels/models/stock_package_type.py
odoo/addons/delivery_package_type_number_parcels/models/stock_quant_package.py
odoo/addons/delivery_package_type_number_parcels/readme/CONTRIBUTORS.md
odoo/addons/delivery_package_type_number_parcels/readme/DESCRIPTION.md
odoo/addons/delivery_package_type_number_parcels/static/description/icon.png
odoo/addons/delivery_package_type_number_parcels/static/description/index.html
odoo/addons/delivery_package_type_number_parcels/tests/__init__.py
odoo/addons/delivery_package_type_number_parcels/tests/test_package_type_number_parcels.py
odoo/addons/delivery_package_type_number_parcels/views/stock_package_type_views.xml
odoo/addons/delivery_package_type_number_parcels/views/stock_quant_package_views.xml
odoo/addons/delivery_package_type_number_parcels/wizards/__init__.py
odoo/addons/delivery_package_type_number_parcels/wizards/choose_delivery_package.py
odoo/addons/delivery_package_type_number_parcels/wizards/choose_delivery_package_views.xml
odoo_addon_delivery_package_type_number_parcels-18.0.1.0.0.2.dist-info/METADATA
odoo_addon_delivery_package_type_number_parcels-18.0.1.0.0.2.dist-info/WHEEL
odoo_addon_delivery_package_type_number_parcels-18.0.1.0.0.2.dist-info/top_level.txt
odoo_addon_delivery_package_type_number_parcels-18.0.1.0.0.2.dist-info/RECORD
