Metadata-Version: 2.1
Name: odoo-addon-delivery_package_type_number_parcels
Version: 18.0.1.0.0.2
Requires-Python: >=3.10
Requires-Dist: odoo==18.0.*
Summary: Number of parcels in a package type
Home-page: https://github.com/OCA/delivery-carrier
License: AGPL-3
Author: ACSONE SA/NV,BCIM,Odoo Community Association (OCA)
Author-email: support@odoo-community.org
Classifier: Programming Language :: Python
Classifier: Framework :: Odoo
Classifier: Framework :: Odoo :: 18.0
Classifier: License :: OSI Approved :: GNU Affero General Public License v3
